{
  "$schema": "https://developer.microsoft.com/json-schemas/fabric/item/report/definition/visualContainer/2.7.0/schema.json",
  "name": "3fdb9a1e135c749602c7",
  "position": {
    "x": 10,
    "y": 575.55555555555554,
    "z": 6001,
    "height": 144.44444444444443,
    "width": 1253.3333333333333
  },
  "visualGroup": {
    "displayName": "Group 1",
    "groupMode": "ScaleMode",
    "objects": {
      "lockAspect": [
        {
          "properties": {
            "show": {
              "expr": {
                "Literal": {
                  "Value": "true"
                }
              }
            }
          }
        }
      ]
    }
  }
}